Workbook

Sheet Summary
A1: Commodity Hedging Simulation: audit report
A2: Karthik Bommisetty | UIC MBA Finance + MS Business Analytics | Fall 2025 hedging game, 7 settled rounds
A4: What happened in the game | B4: Value | C4: Source
A5: Total revenue, hedged | B5: =Settlement!L12 -> 74695500 | C5: Settlement
A6: Total revenue, unhedged | B6: =Settlement!I12 -> 78330000 | C6: Settlement
A7: Cost of hedging | B7: =Settlement!I14 -> 3634500 | C7: Settlement
A8: Cost as % of unhedged revenue | B8: =Settlement!I15 -> 0.046399847 | C8: Settlement
A9: Revenue volatility reduction | B9: =Settlement!I18 -> 0.30406654 | C9: Settlement
A10: Rounds below bankruptcy line, hedged / unhedged | B10: =Settlement!I19&" / "&Settlement!I20 -> 0 / 0 | C10: Settlement
A11: Rounds clearing the investment hurdle, hedged | B11: =Settlement!I21 -> 0 | C11: Settlement
A12: All rounds match my memos | B12: =IF(COUNTIF(Settlement!O5:O11,"Yes")=7,"Yes, 7 of 7","CHECK") -> Yes, 7 of 7 | C12: Settlement
A14: What the stress test says (before each trade) | B14: Value | C14: Source
A15: Volatility per round, estimated from game prices | B15: =Assumptions!B6 -> 0.74438226 | C15: Assumptions
A16: Average 95% VaR reduction across rounds | B16: ='Stress Test'!J12 -> 0.69561986 | C16: Stress Test
A17: Avg P(bankruptcy), unhedged | B17: ='Stress Test'!P12 -> 0.24694 | C17: Stress Test, rounds with a stated line
A18: Avg P(bankruptcy), hedged | B18: ='Stress Test'!O12 -> 0.00954 | C18: Stress Test, rounds with a stated line
A19: Avg P(clear hurdle), unhedged | B19: ='Stress Test'!R12 -> 0.26124 | C19: Stress Test, rounds with a stated hurdle
A20: Avg P(clear hurdle), hedged | B20: ='Stress Test'!Q12 -> 0.18046 | C20: Stress Test, rounds with a stated hurdle
A21: Game's edge on my 3 collars vs market pricing | B21: =SUM('Collar Pricing'!P5:P7) -> 209203.5 | C21: Collar Pricing
A24: Takeaways
A25: At the volatility this game actually had, staying unhedged carried a real chance of hitting the bankruptcy line. My hedges took that close to zero.
A26: The price was the investment: in Rounds 2 to 5 the hedges lowered the chance of funding the project. Only Round 7, with strikes near the hurdle price, raised it.
A27: Strike placement drove the outcome more than hedge ratio. Set the collar call at or above the hurdle price, so the upside given away is upside the firm doesn't need.
A29: Colors: blue = input, black = formula, green = link to another sheet, yellow = key assumption.

Sheet Assumptions
A1: Assumptions
A2: Blue = input you can change. Black = formula. Yellow = key assumption.
A4: Item | B4: Value | C4: Notes
A5: Units produced per round | B5: 100000 | C5: Game setup: producer sells 100,000 units each round.
A6: Volatility per round (σ) | B6: =STDEV(Settlement!R6:R11) -> 0.74438226 | C6: Std dev of round-to-round log changes in the game's settled spot (Settlement col R). Feeds Collar Pricing.
A7: Risk-free rate (annual) | B7: 0.04 | C7: Assumption, used only to discount option premiums.
A8: Pricing horizon per round (years) | B8: 0.083333333 | C8: One round treated as one month for discounting. σ above is already per round.
A9: Annualized σ for Black-76 | B9: =B6/SQRT(B8) -> 2.5786158 | C9: Per-round σ scaled so σ·√T equals one round of volatility.
A10: Monte Carlo scenarios per round | B10: 10000 | C10: Run in Python (src/stress_test.py). Change there and re-run.
A11: Random seed | B11: 2025 | C11: Fixed so every run reproduces the same scenarios.
A12: Forward price used for each round | B12: Swap price | C12: The round's swap price is taken as the market's forward when I traded.
A15: Source for all positions and settled prices: my weekly decision memos, Oct 13 - Dec 2, 2025 (Google Drive, original version history).

Sheet Settlement
A1: Round-by-round settlement
A2: Recomputed from the memos with live formulas. Revenue = units x spot + swap P&L + collar P&L.
A4: Round | B4: Settled spot | C4: Swap qty | D4: Swap price | E4: Collar qty | F4: Put strike | G4: Call strike | H4: Float qty | I4: Unhedged revenue | J4: Swap P&L | K4: Collar P&L | L4: Hedged revenue | M4: Hedge P&L | N4: Memo revenue | O4: Matches memo | P4: Bankruptcy line | Q4: Inv. hurdle | R4: Log change in spot
A5: 1 | B5: 120 | C5: 70000 | D5: 45.25 | E5: 0 | H5: =Assumptions!$B$5-C5-E5 -> 30000 | I5: =Assumptions!$B$5*B5 -> 12000000 | J5: =C5*(D5-B5) -> -5232500 | K5: =IF(E5=0,0,E5*(MAX(F5-B5,0)-MAX(B5-G5,0))) -> 0 | L5: =I5+J5+K5 -> 6767500 | M5: =L5-I5 -> -5232500 | N5: 6767500 | O5: =IF(ABS(L5-N5)<1,"Yes","CHECK") -> Yes
A6: 2 | B6: 140 | C6: 60000 | D6: 115 | E6: 0 | H6: =Assumptions!$B$5-C6-E6 -> 40000 | I6: =Assumptions!$B$5*B6 -> 14000000 | J6: =C6*(D6-B6) -> -1500000 | K6: =IF(E6=0,0,E6*(MAX(F6-B6,0)-MAX(B6-G6,0))) -> 0 | L6: =I6+J6+K6 -> 12500000 | M6: =L6-I6 -> -1500000 | N6: 12500000 | O6: =IF(ABS(L6-N6)<1,"Yes","CHECK") -> Yes | P6: 5000000 | Q6: 15000000 | R6: =LN(B6/B5) -> 0.15415068
A7: 3 | B7: 84 | C7: 70000 | D7: 135 | E7: 0 | H7: =Assumptions!$B$5-C7-E7 -> 30000 | I7: =Assumptions!$B$5*B7 -> 8400000 | J7: =C7*(D7-B7) -> 3570000 | K7: =IF(E7=0,0,E7*(MAX(F7-B7,0)-MAX(B7-G7,0))) -> 0 | L7: =I7+J7+K7 -> 11970000 | M7: =L7-I7 -> 3570000 | N7: 11970000 | O7: =IF(ABS(L7-N7)<1,"Yes","CHECK") -> Yes | P7: 5000000 | Q7: 15000000 | R7: =LN(B7/B6) -> -0.51082562
A8: 4 | B8: 56.5 | C8: 60000 | D8: 85 | E8: 0 | H8: =Assumptions!$B$5-C8-E8 -> 40000 | I8: =Assumptions!$B$5*B8 -> 5650000 | J8: =C8*(D8-B8) -> 1710000 | K8: =IF(E8=0,0,E8*(MAX(F8-B8,0)-MAX(B8-G8,0))) -> 0 | L8: =I8+J8+K8 -> 7360000 | M8: =L8-I8 -> 1710000 | N8: 7360000 | O8: =IF(ABS(L8-N8)<1,"Yes","CHECK") -> Yes | P8: 4000000 | Q8: 11000000 | R8: =LN(B8/B7) -> -0.39657616
A9: 5 | B9: 83.8 | C9: 30000 | D9: 56 | E9: 60000 | F9: 45 | G9: 75 | H9: =Assumptions!$B$5-C9-E9 -> 10000 | I9: =Assumptions!$B$5*B9 -> 8380000 | J9: =C9*(D9-B9) -> -834000 | K9: =IF(E9=0,0,E9*(MAX(F9-B9,0)-MAX(B9-G9,0))) -> -528000 | L9: =I9+J9+K9 -> 7018000 | M9: =L9-I9 -> -1362000 | N9: 7018000 | O9: =IF(ABS(L9-N9)<1,"Yes","CHECK") -> Yes | P9: 4500000 | Q9: 9500000 | R9: =LN(B9/B8) -> 0.39419237
A10: 6 | B10: 225 | C10: 40000 | D10: 75 | E10: 40000 | F10: 70 | G10: 95 | H10: =Assumptions!$B$5-C10-E10 -> 20000 | I10: =Assumptions!$B$5*B10 -> 22500000 | J10: =C10*(D10-B10) -> -6000000 | K10: =IF(E10=0,0,E10*(MAX(F10-B10,0)-MAX(B10-G10,0))) -> -5200000 | L10: =I10+J10+K10 -> 11300000 | M10: =L10-I10 -> -11200000 | N10: 11300000 | O10: =IF(ABS(L10-N10)<1,"Yes","CHECK") -> Yes | R10: =LN(B10/B9) -> 0.98766739
A11: 7 | B11: 74 | C11: 30000 | D11: 210 | E11: 50000 | F11: 200 | G11: 240 | H11: =Assumptions!$B$5-C11-E11 -> 20000 | I11: =Assumptions!$B$5*B11 -> 7400000 | J11: =C11*(D11-B11) -> 4080000 | K11: =IF(E11=0,0,E11*(MAX(F11-B11,0)-MAX(B11-G11,0))) -> 6300000 | L11: =I11+J11+K11 -> 17780000 | M11: =L11-I11 -> 10380000 | N11: 17780000 | O11: =IF(ABS(L11-N11)<1,"Yes","CHECK") -> Yes | P11: 5000000 | Q11: 20000000 | R11: =LN(B11/B10) -> -1.1120353
A12: Total | I12: =SUM(I5:I11) -> 78330000 | J12: =SUM(J5:J11) -> -4206500 | K12: =SUM(K5:K11) -> 572000 | L12: =SUM(L5:L11) -> 74695500 | M12: =SUM(M5:M11) -> -3634500 | N12: =SUM(N5:N11) -> 74695500
A14: Cost of hedging (unhedged - hedged) | I14: =I12-L12 -> 3634500
A15: Cost as % of unhedged revenue | I15: =IF(I12=0,0,I14/I12) -> 0.046399847
A16: Std dev of revenue, hedged | I16: =STDEVP(L5:L11) -> 3693828.9
A17: Std dev of revenue, unhedged | I17: =STDEVP(I5:I11) -> 5307732.9
A18: Volatility reduction from hedging | I18: =IF(I17=0,0,1-I16/I17) -> 0.30406654
A19: Rounds below bankruptcy line, hedged | I19: =SUMPRODUCT((P5:P11<>"")*(L5:L11<P5:P11)) -> 0
A20: Rounds below bankruptcy line, unhedged | I20: =SUMPRODUCT((P5:P11<>"")*(I5:I11<P5:P11)) -> 0
A21: Rounds clearing the hurdle, hedged | I21: =SUMPRODUCT((Q5:Q11<>"")*(L5:L11>=Q5:Q11)) -> 0

Sheet Collar Pricing
A1: Black-76 pricing of each collar I traded
A2: The game settled every collar at zero cost. These formulas price each leg at market and show the zero-cost call strike.
A4: Round | B4: Forward F | C4: Put strike | D4: Game call strike | E4: σ (annual) | F4: r | G4: T (yrs) | H4: d1 put | I4: d2 put | J4: Put premium | K4: d1 call | L4: d2 call | M4: Call premium | N4: Net premium /unit | O4: Collar qty | P4: Game's edge vs market | Q4: Zero-cost call strike | R4: Call premium at zero-cost strike | S4: Solver check | T4: Collar delta /unit | U4: Collar gamma /unit
A5: 5 | B5: =Settlement!D9 -> 56 | C5: =Settlement!F9 -> 45 | D5: =Settlement!G9 -> 75 | E5: =Assumptions!$B$9 -> 2.5786158 | F5: =Assumptions!$B$7 -> 0.04 | G5: =Assumptions!$B$8 -> 0.083333333 | H5: =(LN(B5/C5)+0.5*E5^2*G5)/(E5*SQRT(G5)) -> 0.66597728 | I5: =H5-E5*SQRT(G5) -> -0.078404973 | J5: =EXP(-F5*G5)*(C5*NORMSDIST(-I5)-B5*NORMSDIST(-H5)) -> 9.7217396 | K5: =(LN(B5/D5)+0.5*E5^2*G5)/(E5*SQRT(G5)) -> -0.020263717 | L5: =K5-E5*SQRT(G5) -> -0.76464597 | M5: =EXP(-F5*G5)*(B5*NORMSDIST(K5)-D5*NORMSDIST(L5)) -> 10.843031 | N5: =J5-M5 -> -1.1212912 | O5: =Settlement!E9 -> 60000 | P5: =N5*O5 -> -67277.471 | Q5: 80.3952 | R5: =EXP(-F5*G5)*(B5*NORMSDIST((LN(B5/Q5)+0.5*E5^2*G5)/(E5*SQRT(G5)))-Q5*NORMSDIST((LN(B5/Q5)-0.5*E5^2*G5)/(E5*SQRT(G5)))) -> 9.7217442 | S5: =IF(ABS(R5-J5)<0.01,"Matches put","Re-run solver") -> Matches put | T5: =EXP(-F5*G5)*((NORMSDIST(H5)-1)-NORMSDIST(K5)) -> -0.74215134 | U5: =EXP(-F5*G5)*(EXP(-H5^2/2)-EXP(-K5^2/2))/SQRT(2*PI())/(B5*E5*SQRT(G5)) -> 0.0023662065
A6: 6 | B6: =Settlement!D10 -> 75 | C6: =Settlement!F10 -> 70 | D6: =Settlement!G10 -> 95 | E6: =Assumptions!$B$9 -> 2.5786158 | F6: =Assumptions!$B$7 -> 0.04 | G6: =Assumptions!$B$8 -> 0.083333333 | H6: =(LN(B6/C6)+0.5*E6^2*G6)/(E6*SQRT(G6)) -> 0.46487586 | I6: =H6-E6*SQRT(G6) -> -0.27950639 | J6: =EXP(-F6*G6)*(C6*NORMSDIST(-I6)-B6*NORMSDIST(-H6)) -> 18.567274 | K6: =(LN(B6/D6)+0.5*E6^2*G6)/(E6*SQRT(G6)) -> 0.054627435 | L6: =K6-E6*SQRT(G6) -> -0.68975482 | M6: =EXP(-F6*G6)*(B6*NORMSDIST(K6)-D6*NORMSDIST(L6)) -> 15.78941 | N6: =J6-M6 -> 2.7778648 | O6: =Settlement!E10 -> 40000 | P6: =N6*O6 -> 111114.59 | Q6: 84.6709 | R6: =EXP(-F6*G6)*(B6*NORMSDIST((LN(B6/Q6)+0.5*E6^2*G6)/(E6*SQRT(G6)))-Q6*NORMSDIST((LN(B6/Q6)-0.5*E6^2*G6)/(E6*SQRT(G6)))) -> 18.567288 | S6: =IF(ABS(R6-J6)<0.01,"Matches put","Re-run solver") -> Matches put | T6: =EXP(-F6*G6)*((NORMSDIST(H6)-1)-NORMSDIST(K6)) -> -0.83998791 | U6: =EXP(-F6*G6)*(EXP(-H6^2/2)-EXP(-K6^2/2))/SQRT(2*PI())/(B6*E6*SQRT(G6)) -> 0.00080205407
A7: 7 | B7: =Settlement!D11 -> 210 | C7: =Settlement!F11 -> 200 | D7: =Settlement!G11 -> 240 | E7: =Assumptions!$B$9 -> 2.5786158 | F7: =Assumptions!$B$7 -> 0.04 | G7: =Assumptions!$B$8 -> 0.083333333 | H7: =(LN(B7/C7)+0.5*E7^2*G7)/(E7*SQRT(G7)) -> 0.43773563 | I7: =H7-E7*SQRT(G7) -> -0.30664663 | J7: =EXP(-F7*G7)*(C7*NORMSDIST(-I7)-B7*NORMSDIST(-H7)) -> 54.441307 | K7: =(LN(B7/D7)+0.5*E7^2*G7)/(E7*SQRT(G7)) -> 0.19280562 | L7: =K7-E7*SQRT(G7) -> -0.55157664 | M7: =EXP(-F7*G7)*(B7*NORMSDIST(K7)-D7*NORMSDIST(L7)) -> 51.133979 | N7: =J7-M7 -> 3.3073276 | O7: =Settlement!E11 -> 50000 | P7: =N7*O7 -> 165366.38 | Q7: 228.9924 | R7: =EXP(-F7*G7)*(B7*NORMSDIST((LN(B7/Q7)+0.5*E7^2*G7)/(E7*SQRT(G7)))-Q7*NORMSDIST((LN(B7/Q7)-0.5*E7^2*G7)/(E7*SQRT(G7)))) -> 54.441307 | S7: =IF(ABS(R7-J7)<0.01,"Matches put","Re-run solver") -> Matches put | T7: =EXP(-F7*G7)*((NORMSDIST(H7)-1)-NORMSDIST(K7)) -> -0.90421429 | U7: =EXP(-F7*G7)*(EXP(-H7^2/2)-EXP(-K7^2/2))/SQRT(2*PI())/(B7*E7*SQRT(G7)) -> 0.00020802747
A9: How to read it
A10: Net premium /unit = put premium - call premium. Positive means the collar would have cost money at market prices.
A11: Game's edge vs market = what the game's free collar was worth to me. Positive = the game gave me a better deal than the market would.
A12: If the game's call strike sits above the zero-cost strike, I kept more upside than a real zero-cost collar allows.
A13: Solver check reprices the zero-cost call in Excel. If you change σ or r in Assumptions, re-run src/stress_test.py to refresh column Q.

Sheet Stress Test
A1: Monte Carlo stress test, 10,000 scenarios per round
A2: Each round's actual position run through lognormal settlement prices centered on the forward, at the per-round σ in Assumptions. Values from src/stress_test.py.
A4: Round | B4: Forward | C4: σ per round | D4: Expected rev, hedged ($M) | E4: Expected rev, unhedged ($M) | F4: Std dev, hedged ($M) | G4: Std dev, unhedged ($M) | H4: 95% VaR, hedged ($M) | I4: 95% VaR, unhedged ($M) | J4: VaR reduction | K4: 95% ES, hedged ($M) | L4: 95% ES, unhedged ($M) | M4: Worst case, hedged ($M) | N4: Worst case, unhedged ($M) | O4: P(bankruptcy), hedged | P4: P(bankruptcy), unhedged | Q4: P(clear hurdle), hedged | R4: P(clear hurdle), unhedged
A5: 1 | B5: 45.25 | C5: 0.74438226 | D5: 4.5319505 | E5: 4.5481683 | F5: 1.1923823 | G5: 3.9746075 | H5: 1.0681579 | I5: 3.5605264 | J5: =IF(I5=0,0,1-H5/I5) -> 0.7 | K5: 1.1402001 | L5: 3.8006669 | M5: 3.2124246 | N5: 0.14974872
A6: 2 | B6: 115 | C6: 0.74438226 | D6: 11.523552 | E6: 11.558881 | F6: 4.040485 | G6: 10.101212 | H6: 3.6195407 | I6: 9.0488517 | J6: =IF(I6=0,0,1-H6/I6) -> 0.6 | K6: 3.8636614 | L6: 9.6591534 | M6: 7.0522307 | N6: 0.38057686 | O6: 0 | P6: 0.2234 | Q6: 0.1265 | R6: 0.2355
A7: 3 | B7: 135 | C7: 0.74438226 | D7: 13.520736 | E7: 13.569121 | F7: 3.5573835 | G7: 11.857945 | H7: 3.1867695 | I7: 10.622565 | J7: =IF(I7=0,0,1-H7/I7) -> 0.7 | K7: 3.4017019 | L7: 11.339006 | M7: 9.5840292 | N7: 0.44676414 | O7: 0 | P7: 0.1666 | Q7: 0.215 | R7: 0.3089
A8: 4 | B8: 85 | C8: 0.74438226 | D8: 8.5174082 | E8: 8.5435206 | F8: 2.9864454 | G8: 7.4661135 | H8: 2.6753127 | I8: 6.6882817 | J8: =IF(I8=0,0,1-H8/I8) -> 0.6 | K8: 2.8557497 | L8: 7.1393743 | M8: 5.2125184 | N8: 0.28129594 | O8: 0 | P8: 0.2583 | Q8: 0.1317 | R8: 0.2397
A9: 5 | B9: 56 | C9: 0.74438226 | D9: 5.5432779 | E9: 5.6286724 | F9: 1.1850633 | G9: 4.9188513 | H9: 1.0410504 | I9: 4.4063973 | J9: =IF(I9=0,0,1-H9/I9) -> 0.76374114 | K9: 1.0707695 | L9: 4.7035877 | M9: 4.3985324 | N9: 0.18532438 | O9: 0.0477 | P9: 0.5236 | Q9: 0.0038 | R9: 0.1384
A10: 6 | B10: 75 | C10: 0.74438226 | D10: 7.6236275 | E10: 7.5384005 | F10: 1.6705955 | G10: 6.5877472 | H10: 1.4962324 | I10: 5.901425 | J10: =IF(I10=0,0,1-H10/I10) -> 0.74646252 | K10: 1.575837 | L10: 6.2994479 | M10: 5.8496405 | N10: 0.2482023
A11: 7 | B11: 210 | C11: 0.74438226 | D11: 21.196751 | E11: 21.107521 | F11: 4.3958978 | G11: 18.445692 | H11: 3.9800446 | I11: 16.52399 | J11: =IF(I11=0,0,1-H11/I11) -> 0.75913538 | K11: 4.2029374 | L11: 17.638454 | M11: 16.438993 | N11: 0.69496644 | O11: 0 | P11: 0.0628 | Q11: 0.4253 | R11: 0.3837
A12: Avg | D12: =IFERROR(AVERAGE(D5:D11),"") -> 10.351043 | E12: =IFERROR(AVERAGE(E5:E11),"") -> 10.356326 | F12: =IFERROR(AVERAGE(F5:F11),"") -> 2.7183218 | G12: =IFERROR(AVERAGE(G5:G11),"") -> 9.0503099 | H12: =IFERROR(AVERAGE(H5:H11),"") -> 2.4381583 | I12: =IFERROR(AVERAGE(I5:I11),"") -> 8.1074339 | J12: =IFERROR(AVERAGE(J5:J11),"") -> 0.69561986 | K12: =IFERROR(AVERAGE(K5:K11),"") -> 2.5872653 | ... R12: =IFERROR(AVERAGE(R5:R11),"") -> 0.26124
A14: Blank probability cells = no bankruptcy line or hurdle stated in that round's memo. Hedged revenue never falls below its floor, so 'worst case' is the floor where one exists.

Sheet Vol Sensitivity
A1: How the hedge book behaves as volatility changes
A2: Same 10,000-scenario test re-run at each σ. Rows = σ per round, columns = rounds with stated lines.
A4: VaR reduction from hedging
A5: σ per round | B5: R1 | C5: R2 | D5: R3 | E5: R4 | F5: R5 | G5: R6 | H5: R7
A6: 0.2 | B6: 0.7 | C6: 0.6 | D6: 0.7 | E6: 0.6 | F6: 0.49378742 | G6: 0.66273325 | H6: 0.6787356
A7: 0.35 | B7: 0.7 | C7: 0.6 | D7: 0.7 | E7: 0.6 | F7: 0.64465614 | G7: 0.70502714 | H7: 0.7229123
A8: 0.5 | B8: 0.7 | C8: 0.6 | D8: 0.7 | E8: 0.6 | F8: 0.7099802 | G8: 0.7270728 | H8: 0.7428845
A9: 0.65 | B9: 0.7 | C9: 0.6 | D9: 0.7 | E9: 0.6 | F9: 0.74724745 | G9: 0.74043301 | H9: 0.75418458
A10: 0.8 | B10: 0.7 | C10: 0.6 | D10: 0.7 | E10: 0.6 | F10: 0.77181888 | G10: 0.74945517 | H10: 0.76155452
A11: 0.95 | B11: 0.7 | C11: 0.6 | D11: 0.7 | E11: 0.6 | F11: 0.78939972 | G11: 0.7560591 | H11: 0.76682766
A14: P(clear hurdle): hedged minus unhedged
A15: σ per round | B15: R2 | C15: R3 | D15: R4 | E15: R5 | F15: R7
A16: 0.2 | B16: -0.0745 | C16: -0.2239 | D16: -0.0797 | E16: -0.0041 | F16: 0.1416
A17: 0.35 | B17: -0.1424 | C17: -0.1826 | D17: -0.1422 | E17: -0.0451 | F17: 0.083
A18: 0.5 | B18: -0.1354 | C18: -0.1381 | D18: -0.1359 | E18: -0.094 | F18: 0.0646
A19: 0.65 | B19: -0.1197 | C19: -0.109 | D19: -0.1197 | E19: -0.1235 | F19: 0.0483
A20: 0.8 | B20: -0.1021 | C20: -0.0865 | D20: -0.1009 | E20: -0.1382 | F20: 0.0383
A21: 0.95 | B21: -0.0865 | C21: -0.0718 | D21: -0.0847 | E21: -0.1425 | F21: 0.0299
A24: P(bankruptcy): unhedged minus hedged
A25: σ per round | B25: R2 | C25: R3 | D25: R4 | E25: R5 | F25: R7
A26: 0.2 | B26: 0.0001 | C26: 0 | D26: 0.0002 | E26: 0.1595 | F26: 0
A27: 0.35 | B27: 0.0148 | C27: 0.0042 | D27: 0.0256 | E27: 0.3259 | F27: 0.0001
A28: 0.5 | B28: 0.0817 | C28: 0.044 | D28: 0.105 | E28: 0.4198 | F28: 0.005
A29: 0.65 | B29: 0.1683 | C29: 0.1146 | D29: 0.1982 | E29: 0.467 | F29: 0.0317
A30: 0.8 | B30: 0.258 | C30: 0.1969 | D30: 0.2928 | E30: 0.4788 | F30: 0.0849
A31: 0.95 | B31: 0.3427 | C31: 0.2834 | D31: 0.3722 | E31: 0.4669 | F31: 0.1511
A34: Read it this way: a negative hurdle number means the hedge made the investment less likely to get funded. A positive bankruptcy number means the hedge removed that much bankruptcy probability.
